license
telegram_updates_tweets/__init__.py
telegram_updates_tweets/__main__.py
telegram_updates_tweets/pyproject.toml
telegram_updates_tweets-0.1.5.dist-info/license
telegram_updates_tweets-0.1.5.dist-info/WHEEL
telegram_updates_tweets-0.1.5.dist-info/METADATA
telegram_updates_tweets-0.1.5.dist-info/RECORD
