Metadata-Version: 2.1
Name: telegram-updates-tweets
Version: 0.1.5
Summary: This package monitors the number of participants in a telegram channel and can post gains/losses updates to twitter
Home-page: https://github.com/AlxndrJhn/telegram_updates_tweets
License: MIT
Keywords: twitter-bot,telegram-bot
Author: Alexander Jahn
Author-email: jahn.alexander@gmail.com
Requires-Python: >=3.7,<4.0
Classifier: License :: OSI Approved :: MIT License
Classifier: Programming Language :: Python :: 3
Classifier: Programming Language :: Python :: 3.7
Classifier: Programming Language :: Python :: 3.8
Provides-Extra: logging
Provides-Extra: monitoring
Requires-Dist: Flask (>=1.1.2,<2.0.0); extra == "monitoring"
Requires-Dist: click (>=7.1.2,<8.0.0)
Requires-Dist: matplotlib (>=3.3.3,<4.0.0); extra == "logging"
Requires-Dist: pymongo (>=3.11.2,<4.0.0); extra == "logging"
Requires-Dist: telethon (>=1.18.2,<2.0.0)
Requires-Dist: tweepy (>=3.10.0,<4.0.0)
Requires-Dist: waitress (>=1.4.4,<2.0.0); extra == "monitoring"
Project-URL: Repository, https://github.com/AlxndrJhn/telegram_updates_tweets
